srcignore/__init__.py
srcignore/main.py
srcignore/py.typed
srcignore-0.0.3.dist-info/WHEEL
srcignore-0.0.3.dist-info/entry_points.txt
srcignore-0.0.3.dist-info/METADATA
srcignore-0.0.3.dist-info/RECORD
