Metadata-Version: 2.4
Name: srcignore
Version: 0.0.3
Summary: Generates a list of files that matches .gitignore-like files
Author: Calian AT
License-Expression: MIT
Requires-Dist: gitignore-parser>=0.1.13
Requires-Dist: typer>=0.19.2
Requires-Python: >=3.12
